Metadata-Version: 2.1
Name: linmarg
Version: 0.1.1
Summary: Linear parameters marginalizer
Author-email: Jean-Baptiste Delisle <jean-baptiste.delisle@unige.ch>
Project-URL: Homepage, https://gitlab.unige.ch/delisle/linmarg
Project-URL: Issues, https://gitlab.unige.ch/delisle/linmarg/-/issues
Classifier: Programming Language :: Python :: 3
Classifier: License :: OSI Approved :: European Union Public Licence 1.2 (EUPL 1.2)
Classifier: Operating System :: OS Independent
Requires-Python: >=3.8
License-File: LICENSE
Requires-Dist: numpy
Requires-Dist: scipy
